armory/__init__.py
armory/__version__.py
armory/environ.py
armory/gevent.py
armory/serialize.py
armory/django/__init__.py
armory/django/forms.py
armory/phone/__init__.py
armory/phone/cli.py
armory/phone/lookup.py
armory/phone/phone.py
armory/utils/__init__.py
armory/utils/boolean.py
armory/utils/builtins.py
armory/utils/encoding.py
armory-0.1.3.dist-info/DESCRIPTION.rst
armory-0.1.3.dist-info/METADATA
armory-0.1.3.dist-info/RECORD
armory-0.1.3.dist-info/WHEEL
armory-0.1.3.dist-info/metadata.json
armory-0.1.3.dist-info/top_level.txt
