Metadata-Version: 2.0
Name: armory
Version: 0.1.3
Summary: Python utilities and tools
Home-page: https://github.com/neuroticnerd/armory
Author: Bryce Eggleton
Author-email: eggleton.bryce@gmail.com
License: BSD
Platform: UNKNOWN
Requires-Dist: future
